wordle_helper_uc/__init__.py
wordle_helper_uc/__main__.py
wordle_helper_uc/words.py
wordle_helper_uc-0.2.1.dist-info/METADATA
wordle_helper_uc-0.2.1.dist-info/WHEEL
wordle_helper_uc-0.2.1.dist-info/entry_points.txt
wordle_helper_uc-0.2.1.dist-info/RECORD
