Metadata-Version: 2.1
Name: wordle-helper-uc
Version: 0.2.1
Summary: 
Author: Pedro Juan Royo
Author-email: pedro.juan.royo@gmail.com
Requires-Python: >=3.11,<4.0
Classifier: Programming Language :: Python :: 3
Classifier: Programming Language :: Python :: 3.11
Requires-Dist: requests (>=2.31.0,<3.0.0)
